[
  {
    "date": "2026-03-11",
    "followers": null,
    "following": 276
  },
  {
    "date": "2026-03-14",
    "followers": null,
    "following": 276
  },
  {
    "date": "2026-03-15",
    "followers": null,
    "following": 276
  },
  {
    "date": "2026-03-16",
    "followers": null,
    "following": 276
  },
  {
    "date": "2026-03-17",
    "followers": null,
    "following": 276
  },
  {
    "date": "2026-03-18",
    "followers": null,
    "following": 276
  },
  {
    "date": "2026-03-19",
    "followers": null,
    "following": 276
  },
  {
    "date": "2026-03-20",
    "followers": null,
    "following": 276
  },
  {
    "date": "2026-03-21",
    "followers": 52,
    "following": 276
  },
  {
    "date": "2026-03-22",
    "followers": 61,
    "following": 276
  },
  {
    "date": "2026-03-23",
    "followers": 62,
    "following": 276
  },
  {
    "date": "2026-03-24",
    "followers": 65,
    "following": 276
  },
  {
    "date": "2026-03-25",
    "followers": 70,
    "following": 276
  },
  {
    "date": "2026-03-26",
    "followers": 73,
    "following": 276
  },
  {
    "date": "2026-03-27",
    "followers": 76,
    "following": 276
  },
  {
    "date": "2026-03-28",
    "followers": 76,
    "following": 276
  },
  {
    "date": "2026-03-29",
    "followers": 78,
    "following": 276
  },
  {
    "date": "2026-03-31",
    "followers": 80,
    "following": 276
  },
  {
    "date": "2026-04-01",
    "followers": 80,
    "following": 276
  },
  {
    "date": "2026-04-02",
    "followers": 82,
    "following": 277
  },
  {
    "date": "2026-04-03",
    "followers": 85,
    "following": 277
  },
  {
    "date": "2026-04-04",
    "followers": 86,
    "following": 277
  }
]